LICENSE
MANIFEST.in
README.rst
requirements.txt
setup.cfg
setup.py
safecast_tracker/__init__.py
safecast_tracker/classes.py
safecast_tracker/cmd.py
safecast_tracker/constants.py
safecast_tracker.egg-info/PKG-INFO
safecast_tracker.egg-info/SOURCES.txt
safecast_tracker.egg-info/dependency_links.txt
safecast_tracker.egg-info/entry_points.txt
safecast_tracker.egg-info/not-zip-safe
safecast_tracker.egg-info/pbr.json
safecast_tracker.egg-info/requires.txt
safecast_tracker.egg-info/top_level.txt