Metadata-Version: 1.0
Name: safecast-tracker
Version: 1.0.0
Summary: Safecast Tracker for APRS.
Home-page: https://github.com/ampledata/safecast_tracker
Author: Greg Albrecht
Author-email: gba@orionlabs.co
License: Copyright 2015 Orion Labs, Inc.
